embedd_all/__init__.py
embedd_all/core/__init__.py
embedd_all/core/logger.py
embedd_all/embedd/__init__.py
embedd_all/embedd/index.py
embedd_all/embedd/rag_query.py
embedd_all-0.0.942.dist-info/METADATA
embedd_all-0.0.942.dist-info/WHEEL
embedd_all-0.0.942.dist-info/licenses/LICENSE
embedd_all-0.0.942.dist-info/RECORD
