Metadata-Version: 2.3
Name: embedd-all
Version: 0.0.942
Summary: Embedd (docs, pdfs, excels, csv etc) -> RAG -> Query with LLMs
Project-URL: Homepage, https://github.com/Arnab28122000/embed-all
Project-URL: Repository, https://github.com/Arnab28122000/embed-all
Project-URL: Bug Tracker, https://github.com/Arnab28122000/embed-all/issues
Project-URL: Documentation, https://github.com/Arnab28122000/embed-all/blob/main/README.md
Author-email: Arnab Bhattacharya <arnab.bhattacharya28122000@gmail.com>
Maintainer-email: Arnab Bhattacharya <arnab.bhattacharya28122000@gmail.com>
Requires-Python: >=3.8
Requires-Dist: anthropic>=0.32.0
Requires-Dist: langchain-community>=0.2.2
Requires-Dist: langchain>=0.2.2
Requires-Dist: openai>=1.59.5
Requires-Dist: openpyxl>=3.1.5
Requires-Dist: pandas>=2.2.2
Requires-Dist: pinecone==6.0.2
Requires-Dist: pypandoc-binary>=1.13
Requires-Dist: pypdf>=4.2.0
Requires-Dist: pytest>=8.3.4
Requires-Dist: python-docx>=1.1.2
Requires-Dist: voyageai>=0.2.3
